mlcrate/__init__.py
mlcrate/backend.py
mlcrate/ensemble.py
mlcrate/kaggle.py
mlcrate/models.py
mlcrate/time.py
mlcrate/torch.py
mlcrate/xgb.py
mlcrate-0.2.0.dist-info/DESCRIPTION.rst
mlcrate-0.2.0.dist-info/METADATA
mlcrate-0.2.0.dist-info/RECORD
mlcrate-0.2.0.dist-info/WHEEL
mlcrate-0.2.0.dist-info/metadata.json
mlcrate-0.2.0.dist-info/top_level.txt
