Metadata-Version: 2.0
Name: mlcrate
Version: 0.2.0
Summary: A collection of handy python tools and functions, mainly for ML and Kaggle.
Home-page: https://github.com/mxbi/mlcrate
Author: Mikel Bober-Irizar
Author-email: mikel@mxbi.net
License: MIT
Platform: UNKNOWN
Classifier: License :: OSI Approved :: MIT License
Classifier: Programming Language :: Python :: 3 :: Only
Classifier: Topic :: Scientific/Engineering
Classifier: Development Status :: 4 - Beta
Requires-Dist: numpy
Requires-Dist: pandas
Requires-Dist: pathos
Requires-Dist: tqdm
